[1,["20g1ukYUVPvKWKBRznAKo+@f9941","bdG8q6vX1KcbFDmXyII4Pk@f9941","20g1ukYUVPvKWKBRznAKo+@6c48a","d0MqyYBeFAkIi762QNy1/B@b47c0","6fAc9/gb9Kfr1dCvwZaWSA@b47c0","54TknWPwVPqJqeCR+Y/Czo@f9941","95EkngnxZFbYuFpsqVTaFr@f9941","54TknWPwVPqJqeCR+Y/Czo@6c48a","95EkngnxZFbYuFpsqVTaFr@6c48a","bdG8q6vX1KcbFDmXyII4Pk@6c48a"],["node","_textureSource","_spriteFrame","_cameraComponent","label","button","editBox","scene","_parent","_envmapHDR","_envmapLDR","_backgroundImage","_normalSprite","_hoverSprite","_pressedSprite","_disabledSprite"],["cc.ImageAsset",["cc.Node",["_name","_layer","_objFlags","_active","_parent","_components","_lpos","_children"],-1,1,12,5,2],"cc.SpriteFrame",["cc.Node",["_name","_id","_layer","_objFlags","_components","_parent","_lpos","_lrot","_euler","_children"],-1,9,1,5,5,5,2],["cc.Label",["_string","_actualFontSize","_fontSize","_overflow","_enableWrapText","_horizontalAlign","_verticalAlign","node","_color"],-4,1,5],"cc.TextureCube",["cc.UITransform",["node","_contentSize","_anchorPoint"],3,1,5,5],["cc.Camera",["_clearFlags","_visibility","_projection","_priority","_orthoHeight","_far","node","_color"],-3,1,5],["cc.SceneAsset",["_name"],2],["cc.Node",["_name","_parent","_components","_lpos"],2,1,2,5],["cc.Canvas",["node","_cameraComponent"],3,1,1],["cc.Widget",["_alignFlags","node"],2,1],["0bf66WowvBAZbCQsPdeYoIO",["node","editBox","button","label"],3,1,1,1,1],["cc.Sprite",["_type","_sizeMode","node","_spriteFrame"],1,1,6],["cc.Scene",["_name","_children","_globals"],2,2,4],["cc.SceneGlobals",["ambient","shadows","_skybox","fog","octree","skin","lightProbeInfo","postSettings"],3,4,4,4,4,4,4,4,4],["cc.AmbientInfo",["_skyIllumLDR","_skyColorHDR","_skyColorLDR","_groundAlbedoLDR"],2,5,5,5],["cc.ShadowsInfo",["_enabled","_type","_shadowColor","_size"],1,5,5],["cc.SkyboxInfo",["_envLightingType","_enabled","_envmapHDR","_envmapLDR"],1,6,6],["cc.FogInfo",[],3],["cc.OctreeInfo",[],3],["cc.SkinInfo",["_enabled"],2],["cc.LightProbeInfo",[],3],["cc.PostSettingsInfo",[],3],["cc.DirectionalLight",["_shadowEnabled","_shadowPcf","node","_color","_staticSettings"],1,1,5,4],["cc.StaticLightSettings",["_castShadow"],2],["cc.EditBox",["_inputMode","_maxLength","node","_textLabel","_placeholderLabel"],1,1,1,1],["cc.Button",["_transition","node","_normalColor","_target"],2,1,5,1]],[[6,0,1,1],[6,0,1,2,1],[13,0,1,2,3,3],[8,0,2],[3,0,2,1,9,4,6,4],[3,0,3,2,5,4,4],[3,0,1,5,4,7,8,3],[3,0,1,5,4,6,7,8,3],[1,0,2,1,4,7,5,4],[1,0,1,4,7,5,6,3],[1,0,2,3,1,4,5,6,5],[1,0,2,1,4,5,6,4],[1,0,1,4,5,6,3],[9,0,1,2,3,2],[10,0,1,1],[11,0,1,2],[12,0,1,2,3,1],[14,0,1,2,2],[15,0,1,2,3,4,5,6,7,1],[16,0,1,2,3,2],[17,0,1,2,3,3],[18,0,1,2,3,3],[19,1],[20,1],[21,0,2],[22,1],[23,1],[4,0,1,2,3,4,7,8,6],[4,0,5,1,2,3,4,7,7],[4,0,5,1,2,3,4,7,8,7],[4,0,5,6,1,2,3,7,7],[24,0,1,2,3,4,3],[25,0,2],[7,0,1,6,3],[7,2,3,4,5,0,1,6,7,7],[26,0,1,2,3,4,3],[27,0,1,2,3,2]],[[[{"name":"default_btn_normal","rect":{"x":0,"y":0,"width":40,"height":40},"offset":{"x":0,"y":0},"originalSize":{"width":40,"height":40},"rotated":false,"capInsets":[12,12,12,12],"vertices":{"rawPosition":[-20,-20,0,20,-20,0,-20,20,0,20,20,0],"indexes":[0,1,2,2,1,3],"uv":[0,40,40,40,0,0,40,0],"nuv":[0,0,1,0,0,1,1,1],"minPos":{"x":-20,"y":-20,"z":0},"maxPos":{"x":20,"y":20,"z":0}},"packable":true,"pixelsToUnit":100,"pivot":{"x":0.5,"y":0.5},"meshType":0}],[2],0,[0],[1],[2]],[[[3,"main"],[4,"Canvas",33554432,"7f1fqVm7JBNZ0J2D4sDR1O",[-9,-10,-11,-12],[[0,-1,[5,1280,720]],[14,-3,-2],[15,45,-4],[16,-8,-7,-6,-5]],[1,640,360,0]],[8,"EditBox",512,33554432,1,[-16,-17],[[[0,-13,[5,160,40]],[2,1,0,-14,0],-15],4,4,1]],[9,"Button",33554432,1,[-21],[[[0,-18,[5,100,40]],[2,1,0,-19,1],-20],4,4,1],[1,161.382,0,0]],[17,"main",[-22,-23,1],[18,[19,0.8,[2,0.2,0.5,0.8,0.520833125],[2,0.452588,0.607642,0.755699,0],[2,0.618555,0.577848,0.544564,0]],[20,true,1,[4,4283190348],[0,2048,2048]],[21,1,true,2,3],[22],[23],[24,false],[25],[26]]],[10,"TEXT_LABEL",512,false,33554432,2,[[[1,-24,[5,158,40],[0,0,1]],-25],4,1],[1,-78,20,0]],[11,"PLACEHOLDER_LABEL",512,33554432,2,[[[1,-26,[5,158,40],[0,0,1]],-27],4,1],[1,-78,20,0]],[5,"Label",512,33554432,3,[[0,-28,[5,100,40]],[27,"发送",20,20,1,false,-29,[4,4278190080]]]],[12,"Label",33554432,1,[[[1,-30,[5,160,50.4],[0,0,1]],-31],4,1],[1,-80,-50,0]],[6,"Main Light","c0y6F5f+pAvI805TdmxIjx",4,[[31,true,2,-32,[4,4293982975],[32,true]]],[3,-0.06397656665577071,-0.44608233363525845,-0.8239028751062036,-0.3436591377065261],[1,-117.894,-194.909,38.562]],[7,"Main Camera","c9DMICJLFO5IeO07EPon7U",4,[[33,14,1822425087,-33]],[1,-10,10,10],[3,-0.27781593346944056,-0.36497167621709875,-0.11507512748638377,0.8811195706053617],[1,-35,-45,0]],[13,"Camera",1,[-34],[1,0,0,1000]],[34,0,1073741824,392.6803013993541,2000,6,41943040,11,[4,4278190080]],[28,"",0,40,20,1,false,5],[29,"Enter text here...",0,20,20,1,false,6,[4,4290493371]],[35,6,8,2,13,14],[36,2,3,[4,4292269782],3],[30,"",0,0,20,20,3,8]],0,[0,0,1,0,3,12,0,0,1,0,0,1,0,4,17,0,5,16,0,6,15,0,0,1,0,-1,11,0,-2,2,0,-3,3,0,-4,8,0,0,2,0,0,2,0,-3,15,0,-1,5,0,-2,6,0,0,3,0,0,3,0,-3,16,0,-1,7,0,-1,9,0,-2,10,0,0,5,0,-2,13,0,0,6,0,-2,14,0,0,7,0,0,7,0,0,8,0,-2,17,0,0,9,0,0,10,0,-1,12,0,7,4,1,8,4,34],[0,0,0,0,15,16,16,16,16],[2,2,9,10,11,12,13,14,15],[1,0,3,4,1,0,0,5,6]],[[{"name":"default_btn_pressed","rect":{"x":0,"y":0,"width":40,"height":40},"offset":{"x":0,"y":0},"originalSize":{"width":40,"height":40},"rotated":false,"capInsets":[12,12,12,12],"vertices":{"rawPosition":[-20,-20,0,20,-20,0,-20,20,0,20,20,0],"indexes":[0,1,2,2,1,3],"uv":[0,40,40,40,0,0,40,0],"nuv":[0,0,1,0,0,1,1,1],"minPos":{"x":-20,"y":-20,"z":0},"maxPos":{"x":20,"y":20,"z":0}},"packable":true,"pixelsToUnit":100,"pivot":{"x":0.5,"y":0.5},"meshType":0}],[2],0,[0],[1],[7]],[[{"base":"2,2,0,0,2,0","rgbe":false,"mipmaps":[{"front":"6fAc9/gb9Kfr1dCvwZaWSA@b47c0@e9a6d","back":"6fAc9/gb9Kfr1dCvwZaWSA@b47c0@40c10","left":"6fAc9/gb9Kfr1dCvwZaWSA@b47c0@8fd34","right":"6fAc9/gb9Kfr1dCvwZaWSA@b47c0@74afd","top":"6fAc9/gb9Kfr1dCvwZaWSA@b47c0@bb97f","bottom":"6fAc9/gb9Kfr1dCvwZaWSA@b47c0@7d38f"}]}],[5],0,[],[],[]],[[{"fmt":"0","w":0,"h":0},-1],[0],0,[],[],[]],[[{"fmt":"0","w":0,"h":0},-1],[0],0,[],[],[]],[[{"fmt":"0","w":0,"h":0},-1],[0],0,[],[],[]],[[{"fmt":"0","w":0,"h":0},-1],[0],0,[],[],[]],[[{"fmt":"0","w":0,"h":0},-1],[0],0,[],[],[]],[[{"fmt":"0","w":0,"h":0},-1],[0],0,[],[],[]],[[{"name":"default_btn_disabled","rect":{"x":0,"y":0,"width":40,"height":40},"offset":{"x":0,"y":0},"originalSize":{"width":40,"height":40},"rotated":false,"capInsets":[12,12,12,12],"vertices":{"rawPosition":[-20,-20,0,20,-20,0,-20,20,0,20,20,0],"indexes":[0,1,2,2,1,3],"uv":[0,40,40,40,0,0,40,0],"nuv":[0,0,1,0,0,1,1,1],"minPos":{"x":-20,"y":-20,"z":0},"maxPos":{"x":20,"y":20,"z":0}},"packable":true,"pixelsToUnit":100,"pivot":{"x":0.5,"y":0.5},"meshType":0}],[2],0,[0],[1],[8]],[[{"name":"default_editbox_bg","rect":{"x":0,"y":0,"width":40,"height":40},"offset":{"x":0,"y":0},"originalSize":{"width":40,"height":40},"rotated":false,"capInsets":[12,12,12,12],"vertices":{"rawPosition":[-20,-20,0,20,-20,0,-20,20,0,20,20,0],"indexes":[0,1,2,2,1,3],"uv":[0,40,40,40,0,0,40,0],"nuv":[0,0,1,0,0,1,1,1],"minPos":{"x":-20,"y":-20,"z":0},"maxPos":{"x":20,"y":20,"z":0}},"packable":true,"pixelsToUnit":100,"pivot":{"x":0.5,"y":0.5},"meshType":0}],[2],0,[0],[1],[9]],[[{"base":"2,2,0,0,2,0","rgbe":true,"mipmaps":[{"front":"d0MqyYBeFAkIi762QNy1/B@b47c0@e9a6d","back":"d0MqyYBeFAkIi762QNy1/B@b47c0@40c10","left":"d0MqyYBeFAkIi762QNy1/B@b47c0@8fd34","right":"d0MqyYBeFAkIi762QNy1/B@b47c0@74afd","top":"d0MqyYBeFAkIi762QNy1/B@b47c0@bb97f","bottom":"d0MqyYBeFAkIi762QNy1/B@b47c0@7d38f"}]}],[5],0,[],[],[]],[[{"fmt":"0","w":0,"h":0},-1],[0],0,[],[],[]],[[{"fmt":"0","w":0,"h":0},-1],[0],0,[],[],[]],[[{"fmt":"0","w":0,"h":0},-1],[0],0,[],[],[]],[[{"fmt":"0","w":0,"h":0},-1],[0],0,[],[],[]],[[{"fmt":"0","w":0,"h":0},-1],[0],0,[],[],[]],[[{"fmt":"0","w":0,"h":0},-1],[0],0,[],[],[]]]]
